lib/__init__.py
lib/checkversion.py
lib/dump.py
lib/listapp.py
lib/log.py
Frida_iOS_Hook-3.4.dist-info/LICENSE
Frida_iOS_Hook-3.4.dist-info/METADATA
Frida_iOS_Hook-3.4.dist-info/WHEEL
Frida_iOS_Hook-3.4.dist-info/top_level.txt
Frida_iOS_Hook-3.4.dist-info/RECORD
