Metadata-Version: 2.1
Name: Frida-iOS-Hook
Version: 3.4
Summary: Trace Class/Func & Modify Return Value
Home-page: https://github.com/noobpk/frida-ios-hook/
Author: noobpk
Author-email: ltp.noobpk@gmail.com
License: UNKNOWN
Platform: UNKNOWN
Classifier: Programming Language :: Python :: 3
Classifier: License :: OSI Approved :: MIT License
Classifier: Operating System :: OS Independent
Requires-Python: >=3.0
